alphaviz/__init__.py
alphaviz/cli.py
alphaviz/gui.py
alphaviz/io.py
alphaviz/plotting.py
alphaviz/preprocessing.py
alphaviz/utils.py
alphaviz/__pycache__/__init__.cpython-38.pyc
alphaviz/data/amino_acids.tsv
alphaviz/data/modifications.tsv
alphaviz/docs/alphaviz_tutorial.docx
alphaviz/docs/alphaviz_tutorial.pdf
alphaviz/docs/~$phaviz_tutorial.docx
alphaviz/img/github.png
alphaviz/img/max-planck-gesellschaft.jpg
alphaviz/img/mpi_logo.png
alphaviz/style/dashboard_style.css
alphaviz/style/tables_formatting.json
alphaviz-1.1.15.dist-info/LICENSE.txt
alphaviz-1.1.15.dist-info/METADATA
alphaviz-1.1.15.dist-info/WHEEL
alphaviz-1.1.15.dist-info/entry_points.txt
alphaviz-1.1.15.dist-info/top_level.txt
alphaviz-1.1.15.dist-info/RECORD
