Metadata-Version: 2.1
Name: alphaviz
Version: 1.1.15
Summary: A interactive Dashboard to explore mass spectrometry data.
Home-page: https://github.com/MannLabs/alphaviz
Author: Eugenia Voytik
Author-email: opensource@alphapept.com
License: Apache
Project-URL: Mann Labs at MPIB, https://www.biochem.mpg.de/mann
Project-URL: GitHub:, https://github.com/MannLabs/alphaviz
Keywords: ms,mass spectrometry,bruker,timsTOF,proteomics,bioinformatics,visualization
Platform: UNKNOWN
Classifier: Development Status :: 4 - Beta
Classifier: Intended Audience :: Science/Research
Classifier: License :: OSI Approved :: Apache Software License
Classifier: Operating System :: OS Independent
Classifier: Programming Language :: Python :: 3
Classifier: Programming Language :: Python :: 3.8
Classifier: Programming Language :: Python :: 3 :: Only
Classifier: Topic :: Scientific/Engineering :: Bio-Informatics
Requires-Python: >=3.8,<3.9
License-File: LICENSE.txt
Requires-Dist: alphatims
Requires-Dist: peptdeep
Requires-Dist: alphabase
Requires-Dist: pywin32 (==225) ; sys_platform == "win32"
Provides-Extra: development
Requires-Dist: jupyter ; extra == 'development'
Requires-Dist: jupyter-contrib-nbextensions ; extra == 'development'
Requires-Dist: pyinstaller ; extra == 'development'
Requires-Dist: autodocsumm ; extra == 'development'
Requires-Dist: sphinx-rtd-theme ; extra == 'development'
Requires-Dist: twine ; extra == 'development'
Requires-Dist: bumpversion ; extra == 'development'
Requires-Dist: pipdeptree ; extra == 'development'
Requires-Dist: ipykernel ; extra == 'development'
Requires-Dist: tqdm ; extra == 'development'
Requires-Dist: psutil ; extra == 'development'
Requires-Dist: pytest ; extra == 'development'
Provides-Extra: development-stable
Requires-Dist: jupyter (==1.0.0) ; extra == 'development-stable'
Requires-Dist: jupyter-contrib-nbextensions (==0.5.1) ; extra == 'development-stable'
Requires-Dist: pyinstaller (==4.10) ; extra == 'development-stable'
Requires-Dist: autodocsumm (==0.2.6) ; extra == 'development-stable'
Requires-Dist: sphinx-rtd-theme (==0.5.2) ; extra == 'development-stable'
Requires-Dist: twine (==3.4.1) ; extra == 'development-stable'
Requires-Dist: bumpversion (==0.6.0) ; extra == 'development-stable'
Requires-Dist: pipdeptree (==2.1.0) ; extra == 'development-stable'
Requires-Dist: ipykernel (==6.4.0) ; extra == 'development-stable'
Requires-Dist: tqdm (==4.61.1) ; extra == 'development-stable'
Requires-Dist: psutil (==5.8.0) ; extra == 'development-stable'
Requires-Dist: pytest (==6.2.5) ; extra == 'development-stable'
Provides-Extra: gui
Requires-Dist: bokeh ; extra == 'gui'
Requires-Dist: matplotlib ; extra == 'gui'
Requires-Dist: datashader ; extra == 'gui'
Requires-Dist: holoviews ; extra == 'gui'
Requires-Dist: panel ; extra == 'gui'
Requires-Dist: pyteomics ; extra == 'gui'
Requires-Dist: plotly ; extra == 'gui'
Requires-Dist: beautifulsoup4 ; extra == 'gui'
Requires-Dist: requests ; extra == 'gui'
Requires-Dist: jinja2 ; extra == 'gui'
Provides-Extra: gui-stable
Requires-Dist: bokeh (==2.4.2) ; extra == 'gui-stable'
Requires-Dist: matplotlib (==3.4.3) ; extra == 'gui-stable'
Requires-Dist: datashader (==0.13.0) ; extra == 'gui-stable'
Requires-Dist: holoviews (==1.14.8) ; extra == 'gui-stable'
Requires-Dist: panel (==0.12.4) ; extra == 'gui-stable'
Requires-Dist: pyteomics (==4.5) ; extra == 'gui-stable'
Requires-Dist: plotly (==5.8.0) ; extra == 'gui-stable'
Requires-Dist: beautifulsoup4 (==4.10.0) ; extra == 'gui-stable'
Requires-Dist: requests (==2.27.1) ; extra == 'gui-stable'
Requires-Dist: jinja2 (==3.0.2) ; extra == 'gui-stable'
Provides-Extra: stable
Requires-Dist: alphatims (==0.3.0) ; extra == 'stable'
Requires-Dist: peptdeep (==0.0.5) ; extra == 'stable'
Requires-Dist: alphabase (==0.0.5) ; extra == 'stable'
